cubicweb_fresh/__init__.py
cubicweb_fresh/__pkginfo__.py
cubicweb_fresh/entities.py
cubicweb_fresh/hooks.py
cubicweb_fresh/schema.py
cubicweb_fresh/sobjects.py
cubicweb_fresh/data/accounting-entries.xsl
cubicweb_fresh/i18n/en.po
cubicweb_fresh/i18n/fr.po
cubicweb_fresh/migration/0.5.0_Any.py
cubicweb_fresh/migration/0.5.1_Any.py
cubicweb_fresh/migration/0.7.0_Any.py
cubicweb_fresh/migration/0.7.1_Any.py
cubicweb_fresh/migration/1.0.1_Any.py
cubicweb_fresh/migration/1.1.0_Any.py
cubicweb_fresh/migration/1.3.0_Any.py
cubicweb_fresh/migration/1.9.0_Any.py
cubicweb_fresh/migration/postcreate.py
cubicweb_fresh/views/__init__.py
cubicweb_fresh/views/accounting.py
cubicweb_fresh/views/actions.py
cubicweb_fresh-1.12.1.dist-info/METADATA
cubicweb_fresh-1.12.1.dist-info/WHEEL
cubicweb_fresh-1.12.1.dist-info/entry_points.txt
cubicweb_fresh-1.12.1.dist-info/top_level.txt
cubicweb_fresh-1.12.1.dist-info/RECORD
