Metadata-Version: 2.4
Name: cubicweb-fresh
Version: 1.12.1
Summary: expense tracking application built on the CubicWeb framework
Home-page: http://www.cubicweb.org/project/cubicweb-fresh
Author: Logilab
Author-email: contact@logilab.fr
License: LGPL
Classifier: Environment :: Web Environment
Classifier: Framework :: CubicWeb
Classifier: Programming Language :: Python
Classifier: Programming Language :: JavaScript
Requires-Dist: cubicweb[s3]<6.0.0,>=5.0.1
Requires-Dist: cubicweb-api<0.18.0,>=0.17.1
Requires-Dist: cubicweb-expense<2.0.0,>=1.1.0
Requires-Dist: cubicweb-workcase<2.0.0,>=1.0.0
Requires-Dist: cubicweb-searchui<2.0.0,>=1.1.0
Requires-Dist: cubicweb-prometheus<1.0.0,>=0.6.0
Requires-Dist: cubicweb-signedrequest<4.0.0,>=3.3.1
Requires-Dist: cubicweb-sentry<2.0.0,>=1.1.0
Requires-Dist: cubicweb-card<3.0.0,>=2.1.0
Requires-Dist: cubicweb-oauth2<2.0.0,>=1.2.1
Requires-Dist: cubicweb-web<2.0.0,>=1.6.2
Requires-Dist: reportlab<3.7.0,>=3.6.0
Requires-Dist: cwclientlib<2.0.0,>=1.6.0
Dynamic: author
Dynamic: author-email
Dynamic: classifier
Dynamic: description
Dynamic: home-page
Dynamic: license
Dynamic: requires-dist
Dynamic: summary
